CHANGELOG.md
MANIFEST.in
README.md
basicevents.py
setup.py
basicevents.egg-info/PKG-INFO
basicevents.egg-info/SOURCES.txt
basicevents.egg-info/dependency_links.txt
basicevents.egg-info/not-zip-safe
basicevents.egg-info/top_level.txt