Metadata-Version: 1.1
Name: basicevents
Version: 2.0.13
Summary: python events non-blocking
Home-page: https://github.com/agalera/basicevents
Author: Alberto Galera Jimenez
Author-email: galerajimenez@gmail.com
License: GPL
Keywords: basicevents
Platform: UNKNOWN
Classifier: Development Status :: 4 - Beta
Classifier: Topic :: Software Development :: Libraries :: Python Modules
Classifier: Intended Audience :: Developers
Classifier: License :: OSI Approved :: GNU General Public License (GPL)
Classifier: Natural Language :: English
Classifier: Programming Language :: Python :: 2
Classifier: Programming Language :: Python :: 2.6
Classifier: Programming Language :: Python :: 2.7
Classifier: Programming Language :: Python :: 3
Classifier: Programming Language :: Python :: 3.3
Classifier: Programming Language :: Python :: 3.4
Classifier: Programming Language :: Python :: 3.5
